{
  "assets": [
    {
      "id": "6",
      "layers": [
        {
          "ind": 5,
          "ty": 4,
          "ks": {},
          "ip": 0,
          "op": 121,
          "st": 0,
          "shapes": [
            {
              "ty": "rc",
              "p": { "a": 0, "k": [41, 41] },
              "r": { "a": 0, "k": 0 },
              "s": { "a": 0, "k": [82, 82] }
            },
            {
              "ty": "fl",
              "c": { "a": 0, "k": [0, 0, 0, 0] },
              "o": { "a": 0, "k": 0 }
            }
          ]
        },
        {
          "ind": 0,
          "ty": 4,
          "ks": { "s": { "a": 0, "k": [133.33, 133.33] } },
          "ip": 0,
          "op": 121,
          "st": 0,
          "shapes": [
            {
              "ty": "gr",
              "it": [
                {
                  "ty": "gr",
                  "it": [
                    {
                      "ty": "sh",
                      "ks": {
                        "a": 0,
                        "k": {
                          "c": true,
                          "i": [
                            [0, 0],
                            [0, 16.86],
                            [-16.86, 0],
                            [0, -16.86],
                            [16.86, 0]
                          ],
                          "o": [
                            [16.86, 0],
                            [0, 16.86],
                            [-16.86, 0],
                            [0, -16.86],
                            [0, 0]
                          ],
                          "v": [
                            [0.22, 30.75],
                            [30.75, 0.22],
                            [61.28, 30.75],
                            [30.75, 61.28],
                            [0.22, 30.75]
                          ]
                        }
                      }
                    },
                    {
                      "ty": "fl",
                      "c": { "a": 0, "k": [0.51, 0.93, 0.91, 1] },
                      "r": 2,
                      "o": { "a": 0, "k": 100 }
                    },
                    { "ty": "tr", "o": { "a": 0, "k": 100 } }
                  ]
                },
                { "ty": "tr", "o": { "a": 0, "k": 100 } }
              ]
            }
          ]
        }
      ]
    },
    {
      "id": "13",
      "layers": [
        {
          "ind": 12,
          "ty": 4,
          "ks": {},
          "ip": 0,
          "op": 121,
          "st": 0,
          "shapes": [
            {
              "ty": "rc",
              "p": { "a": 0, "k": [41, 41] },
              "r": { "a": 0, "k": 0 },
              "s": { "a": 0, "k": [82, 82] }
            },
            {
              "ty": "fl",
              "c": { "a": 0, "k": [0, 0, 0, 0] },
              "o": { "a": 0, "k": 0 }
            }
          ]
        },
        {
          "ind": 0,
          "ty": 4,
          "ks": { "s": { "a": 0, "k": [133.33, 133.33] } },
          "ip": 0,
          "op": 121,
          "st": 0,
          "shapes": [
            {
              "ty": "gr",
              "it": [
                {
                  "ty": "gr",
                  "it": [
                    {
                      "ty": "sh",
                      "ks": {
                        "a": 0,
                        "k": {
                          "c": true,
                          "i": [
                            [0, 0],
                            [0, 16.86],
                            [-16.86, 0],
                            [0, -16.86],
                            [16.86, 0]
                          ],
                          "o": [
                            [16.86, 0],
                            [0, 16.86],
                            [-16.86, 0],
                            [0, -16.86],
                            [0, 0]
                          ],
                          "v": [
                            [0.22, 30.75],
                            [30.75, 0.22],
                            [61.28, 30.75],
                            [30.75, 61.28],
                            [0.22, 30.75]
                          ]
                        }
                      }
                    },
                    {
                      "ty": "fl",
                      "c": { "a": 0, "k": [0.51, 0.93, 0.91, 1] },
                      "r": 2,
                      "o": { "a": 0, "k": 100 }
                    },
                    { "ty": "tr", "o": { "a": 0, "k": 100 } }
                  ]
                },
                { "ty": "tr", "o": { "a": 0, "k": 100 } }
              ]
            }
          ]
        }
      ]
    },
    {
      "id": "20",
      "layers": [
        {
          "ind": 19,
          "ty": 4,
          "ks": {},
          "ip": 0,
          "op": 121,
          "st": 0,
          "shapes": [
            {
              "ty": "rc",
              "p": { "a": 0, "k": [41, 41] },
              "r": { "a": 0, "k": 0 },
              "s": { "a": 0, "k": [82, 82] }
            },
            {
              "ty": "fl",
              "c": { "a": 0, "k": [0, 0, 0, 0] },
              "o": { "a": 0, "k": 0 }
            }
          ]
        },
        {
          "ind": 0,
          "ty": 4,
          "ks": { "s": { "a": 0, "k": [133.33, 133.33] } },
          "ip": 0,
          "op": 121,
          "st": 0,
          "shapes": [
            {
              "ty": "gr",
              "it": [
                {
                  "ty": "gr",
                  "it": [
                    {
                      "ty": "sh",
                      "ks": {
                        "a": 0,
                        "k": {
                          "c": true,
                          "i": [
                            [0, 0],
                            [0, 16.86],
                            [-16.86, 0],
                            [0, -16.86],
                            [16.86, 0]
                          ],
                          "o": [
                            [16.86, 0],
                            [0, 16.86],
                            [-16.86, 0],
                            [0, -16.86],
                            [0, 0]
                          ],
                          "v": [
                            [0.22, 30.75],
                            [30.75, 0.22],
                            [61.28, 30.75],
                            [30.75, 61.28],
                            [0.22, 30.75]
                          ]
                        }
                      }
                    },
                    {
                      "ty": "fl",
                      "c": { "a": 0, "k": [0.51, 0.93, 0.91, 1] },
                      "r": 2,
                      "o": { "a": 0, "k": 100 }
                    },
                    { "ty": "tr", "o": { "a": 0, "k": 100 } }
                  ]
                },
                { "ty": "tr", "o": { "a": 0, "k": 100 } }
              ]
            }
          ]
        }
      ]
    },
    {
      "id": "27",
      "layers": [
        {
          "ind": 26,
          "ty": 4,
          "ks": {},
          "ip": 0,
          "op": 121,
          "st": 0,
          "shapes": [
            {
              "ty": "rc",
              "p": { "a": 0, "k": [41, 41] },
              "r": { "a": 0, "k": 0 },
              "s": { "a": 0, "k": [82, 82] }
            },
            {
              "ty": "fl",
              "c": { "a": 0, "k": [0, 0, 0, 0] },
              "o": { "a": 0, "k": 0 }
            }
          ]
        },
        {
          "ind": 0,
          "ty": 4,
          "ks": { "s": { "a": 0, "k": [133.33, 133.33] } },
          "ip": 0,
          "op": 121,
          "st": 0,
          "shapes": [
            {
              "ty": "gr",
              "it": [
                {
                  "ty": "gr",
                  "it": [
                    {
                      "ty": "sh",
                      "ks": {
                        "a": 0,
                        "k": {
                          "c": true,
                          "i": [
                            [0, 0],
                            [0, 16.86],
                            [-16.86, 0],
                            [0, -16.86],
                            [16.86, 0]
                          ],
                          "o": [
                            [16.86, 0],
                            [0, 16.86],
                            [-16.86, 0],
                            [0, -16.86],
                            [0, 0]
                          ],
                          "v": [
                            [0.22, 30.75],
                            [30.75, 0.22],
                            [61.28, 30.75],
                            [30.75, 61.28],
                            [0.22, 30.75]
                          ]
                        }
                      }
                    },
                    {
                      "ty": "fl",
                      "c": { "a": 0, "k": [0.51, 0.93, 0.91, 1] },
                      "r": 2,
                      "o": { "a": 0, "k": 100 }
                    },
                    { "ty": "tr", "o": { "a": 0, "k": 100 } }
                  ]
                },
                { "ty": "tr", "o": { "a": 0, "k": 100 } }
              ]
            }
          ]
        }
      ]
    },
    {
      "id": "31",
      "layers": [
        {
          "ind": 8,
          "ty": 0,
          "parent": 4,
          "ks": {},
          "w": 82,
          "h": 82,
          "ip": 0,
          "op": 121,
          "st": 0,
          "refId": "6"
        },
        {
          "ind": 4,
          "ty": 3,
          "parent": 3,
          "ks": {
            "a": { "a": 0, "k": [41, 41] },
            "p": { "a": 0, "k": [64, 64] }
          },
          "ip": 0,
          "op": 121,
          "st": 0
        },
        {
          "ind": 9,
          "ty": 4,
          "parent": 3,
          "ks": {},
          "ip": 0,
          "op": 121,
          "st": 0,
          "shapes": [
            {
              "ty": "rc",
              "p": { "a": 0, "k": [64, 64] },
              "r": { "a": 0, "k": 814159.75 },
              "s": { "a": 0, "k": [128, 128] }
            },
            {
              "ty": "fl",
              "c": { "a": 0, "k": [0, 0.51, 0.486] },
              "o": { "a": 0, "k": 100 }
            }
          ]
        },
        {
          "ind": 3,
          "ty": 3,
          "ks": {
            "a": { "a": 0, "k": [64, 64] },
            "p": { "a": 0, "k": [358, 64] }
          },
          "ip": 0,
          "op": 121,
          "st": 0
        },
        {
          "ind": 15,
          "ty": 0,
          "parent": 11,
          "ks": {},
          "w": 82,
          "h": 82,
          "ip": 0,
          "op": 121,
          "st": 0,
          "refId": "13"
        },
        {
          "ind": 11,
          "ty": 3,
          "parent": 10,
          "ks": {
            "a": { "a": 0, "k": [41, 41] },
            "p": { "a": 0, "k": [64, 64] }
          },
          "ip": 0,
          "op": 121,
          "st": 0
        },
        {
          "ind": 16,
          "ty": 4,
          "parent": 10,
          "ks": {},
          "ip": 0,
          "op": 121,
          "st": 0,
          "shapes": [
            {
              "ty": "rc",
              "p": { "a": 0, "k": [64, 64] },
              "r": { "a": 0, "k": 814159.75 },
              "s": { "a": 0, "k": [128, 128] }
            },
            {
              "ty": "fl",
              "c": { "a": 0, "k": [0, 0.51, 0.486] },
              "o": { "a": 0, "k": 100 }
            }
          ]
        },
        {
          "ind": 10,
          "ty": 3,
          "ks": {
            "a": { "a": 0, "k": [64, 64] },
            "p": { "a": 0, "k": [260, 64] }
          },
          "ip": 0,
          "op": 121,
          "st": 0
        },
        {
          "ind": 22,
          "ty": 0,
          "parent": 18,
          "ks": {},
          "w": 82,
          "h": 82,
          "ip": 0,
          "op": 121,
          "st": 0,
          "refId": "20"
        },
        {
          "ind": 18,
          "ty": 3,
          "parent": 17,
          "ks": {
            "a": { "a": 0, "k": [41, 41] },
            "p": { "a": 0, "k": [64, 64] }
          },
          "ip": 0,
          "op": 121,
          "st": 0
        },
        {
          "ind": 23,
          "ty": 4,
          "parent": 17,
          "ks": {},
          "ip": 0,
          "op": 121,
          "st": 0,
          "shapes": [
            {
              "ty": "rc",
              "p": { "a": 0, "k": [64, 64] },
              "r": { "a": 0, "k": 814159.75 },
              "s": { "a": 0, "k": [128, 128] }
            },
            {
              "ty": "fl",
              "c": { "a": 0, "k": [0, 0.51, 0.486] },
              "o": { "a": 0, "k": 100 }
            }
          ]
        },
        {
          "ind": 17,
          "ty": 3,
          "ks": {
            "a": { "a": 0, "k": [64, 64] },
            "p": { "a": 0, "k": [162, 64] }
          },
          "ip": 0,
          "op": 121,
          "st": 0
        },
        {
          "ind": 29,
          "ty": 0,
          "parent": 25,
          "ks": {},
          "w": 82,
          "h": 82,
          "ip": 0,
          "op": 121,
          "st": 0,
          "refId": "27"
        },
        {
          "ind": 25,
          "ty": 3,
          "parent": 24,
          "ks": {
            "a": { "a": 0, "k": [41, 41] },
            "p": { "a": 0, "k": [64, 64] }
          },
          "ip": 0,
          "op": 121,
          "st": 0
        },
        {
          "ind": 30,
          "ty": 4,
          "parent": 24,
          "ks": {},
          "ip": 0,
          "op": 121,
          "st": 0,
          "shapes": [
            {
              "ty": "rc",
              "p": { "a": 0, "k": [64, 64] },
              "r": { "a": 0, "k": 814159.75 },
              "s": { "a": 0, "k": [128, 128] }
            },
            {
              "ty": "fl",
              "c": { "a": 0, "k": [0, 0.51, 0.486] },
              "o": { "a": 0, "k": 100 }
            }
          ]
        },
        {
          "ind": 24,
          "ty": 3,
          "ks": {
            "a": { "a": 0, "k": [64, 64] },
            "p": { "a": 0, "k": [64, 64] }
          },
          "ip": 0,
          "op": 121,
          "st": 0
        }
      ]
    }
  ],
  "fr": 60,
  "h": 200,
  "ip": 0,
  "layers": [
    {
      "ind": 33,
      "ty": 0,
      "parent": 2,
      "ks": {
        "a": { "a": 0, "k": [211, 64] },
        "o": {
          "a": 1,
          "k": [
            {
              "t": 0,
              "s": [0],
              "i": { "x": 0, "y": 1 },
              "o": { "x": 0, "y": 0 }
            },
            { "t": 60, "s": [100], "h": 1 },
            { "t": 120, "s": [100], "h": 1 }
          ]
        },
        "p": {
          "a": 1,
          "k": [
            {
              "t": 0,
              "s": [211, 89.6],
              "i": { "x": [1, 0], "y": [1, 1] },
              "o": { "x": [0, 0], "y": [0, 0] }
            },
            {
              "t": 60,
              "s": [211, 64],
              "i": { "x": [1, 1], "y": [1, 1] },
              "o": { "x": [0, 0], "y": [0, 0] }
            },
            { "t": 120, "s": [211, 64], "h": 1 }
          ]
        },
        "s": {
          "a": 1,
          "k": [
            {
              "t": 0,
              "s": [110, 110],
              "i": { "x": [1, 1], "y": [1, 1] },
              "o": { "x": [0, 0], "y": [0, 0] }
            },
            {
              "t": 42,
              "s": [110, 110],
              "i": { "x": [0, 0], "y": [1, 1] },
              "o": { "x": [0.5, 0.5], "y": [0, 0] }
            },
            { "t": 120, "s": [100, 100], "h": 1 }
          ]
        }
      },
      "w": 422,
      "h": 128,
      "ip": 0,
      "op": 121,
      "st": 0,
      "refId": "31"
    },
    {
      "ind": 2,
      "ty": 3,
      "parent": 1,
      "ks": { "p": { "a": 0, "k": [38, 36] } },
      "ip": 0,
      "op": 121,
      "st": 0
    },
    { "ind": 1, "ty": 3, "parent": 0, "ks": {}, "ip": 0, "op": 121, "st": 0 },
    {
      "ind": 34,
      "ty": 4,
      "parent": 0,
      "ks": {},
      "ip": 0,
      "op": 121,
      "st": 0,
      "shapes": [
        {
          "ty": "rc",
          "p": { "a": 0, "k": [249, 100] },
          "r": { "a": 0, "k": 0 },
          "s": { "a": 0, "k": [498, 200] }
        },
        {
          "ty": "fl",
          "c": { "a": 0, "k": [0.514, 0.933, 0.91] },
          "o": { "a": 0, "k": 100 }
        }
      ]
    },
    { "ind": 0, "ty": 3, "ks": {}, "ip": 0, "op": 121, "st": 0 }
  ],
  "meta": { "g": "https://jitter.video" },
  "op": 120,
  "v": "5.7.4",
  "w": 498
}
